{"openapi":"3.1.0","info":{"title":"Gantry Board API","description":"AI Agent Orchestration Kanban Board API","license":{"name":"Apache-2.0","identifier":"Apache-2.0"},"version":"0.1.0"},"paths":{"/api/projects":{"get":{"tags":["projects"],"operationId":"list_projects","responses":{"200":{"description":"List all projects","content":{"application/json":{"schema":{"type":"array","items":{"$ref":"#/components/schemas/Project"}}}}}}},"post":{"tags":["projects"],"operationId":"create_project","requestBody":{"content":{"application/json":{"schema":{"$ref":"#/components/schemas/CreateProjectRequest"}}},"required":true},"responses":{"201":{"description":"Project created","content":{"application/json":{"schema":{"$ref":"#/components/schemas/Project"}}}}}}},"/api/projects/{id}":{"get":{"tags":["projects"],"operationId":"get_project","parameters":[{"name":"id","in":"path","description":"Project ID","required":true,"schema":{"type":"string","format":"uuid"}}],"responses":{"200":{"description":"Project found","content":{"application/json":{"schema":{"$ref":"#/components/schemas/Project"}}}},"404":{"description":"Project not found"}}},"delete":{"tags":["projects"],"operationId":"delete_project","parameters":[{"name":"id","in":"path","description":"Project ID","required":true,"schema":{"type":"string","format":"uuid"}}],"responses":{"204":{"description":"Project deleted"},"404":{"description":"Project not found"}}},"patch":{"tags":["projects"],"operationId":"update_project","parameters":[{"name":"id","in":"path","description":"Project ID","required":true,"schema":{"type":"string","format":"uuid"}}],"requestBody":{"content":{"application/json":{"schema":{"$ref":"#/components/schemas/UpdateProjectRequest"}}},"required":true},"responses":{"200":{"description":"Project updated","content":{"application/json":{"schema":{"$ref":"#/components/schemas/Project"}}}},"404":{"description":"Project not found"}}}},"/api/projects/{project_id}/members":{"get":{"tags":["project-members"],"operationId":"list_members","parameters":[{"name":"project_id","in":"path","description":"Project ID","required":true,"schema":{"type":"string","format":"uuid"}}],"responses":{"200":{"description":"List project members","content":{"application/json":{"schema":{"type":"array","items":{"$ref":"#/components/schemas/ProjectMember"}}}}},"404":{"description":"Project not found"}}},"post":{"tags":["project-members"],"operationId":"add_member","parameters":[{"name":"project_id","in":"path","description":"Project ID","required":true,"schema":{"type":"string","format":"uuid"}}],"requestBody":{"content":{"application/json":{"schema":{"$ref":"#/components/schemas/AddMemberRequest"}}},"required":true},"responses":{"201":{"description":"Member added","content":{"application/json":{"schema":{"$ref":"#/components/schemas/ProjectMember"}}}},"404":{"description":"Project not found"}}}},"/api/projects/{project_id}/members/{user_id}":{"get":{"tags":["project-members"],"operationId":"get_member","parameters":[{"name":"project_id","in":"path","description":"Project ID","required":true,"schema":{"type":"string","format":"uuid"}},{"name":"user_id","in":"path","description":"User ID","required":true,"schema":{"type":"string","format":"uuid"}}],"responses":{"200":{"description":"Member found","content":{"application/json":{"schema":{"$ref":"#/components/schemas/ProjectMember"}}}},"404":{"description":"Member not found"}}},"delete":{"tags":["project-members"],"operationId":"remove_member","parameters":[{"name":"project_id","in":"path","description":"Project ID","required":true,"schema":{"type":"string","format":"uuid"}},{"name":"user_id","in":"path","description":"User ID","required":true,"schema":{"type":"string","format":"uuid"}}],"responses":{"204":{"description":"Member removed"},"404":{"description":"Member not found"}}},"patch":{"tags":["project-members"],"operationId":"update_member","parameters":[{"name":"project_id","in":"path","description":"Project ID","required":true,"schema":{"type":"string","format":"uuid"}},{"name":"user_id","in":"path","description":"User ID","required":true,"schema":{"type":"string","format":"uuid"}}],"requestBody":{"content":{"application/json":{"schema":{"$ref":"#/components/schemas/UpdateMemberRequest"}}},"required":true},"responses":{"200":{"description":"Member role updated","content":{"application/json":{"schema":{"$ref":"#/components/schemas/ProjectMember"}}}},"404":{"description":"Member not found"}}}},"/api/tasks":{"get":{"tags":["tasks"],"operationId":"list_tasks","parameters":[{"name":"project_id","in":"query","description":"Filter by project ID","required":true,"schema":{"type":"string","format":"uuid"}}],"responses":{"200":{"description":"List tasks for project","content":{"application/json":{"schema":{"type":"array","items":{"$ref":"#/components/schemas/Task"}}}}},"404":{"description":"Project not found"}}},"post":{"tags":["tasks"],"operationId":"create_task","requestBody":{"content":{"application/json":{"schema":{"$ref":"#/components/schemas/CreateTaskRequest"}}},"required":true},"responses":{"201":{"description":"Task created","content":{"application/json":{"schema":{"$ref":"#/components/schemas/Task"}}}},"400":{"description":"Validation error"},"404":{"description":"Project not found"}}}},"/api/tasks/{id}":{"get":{"tags":["tasks"],"operationId":"get_task","parameters":[{"name":"id","in":"path","description":"Task ID","required":true,"schema":{"type":"string","format":"uuid"}}],"responses":{"200":{"description":"Task found","content":{"application/json":{"schema":{"$ref":"#/components/schemas/Task"}}}},"404":{"description":"Task not found"}}},"delete":{"tags":["tasks"],"operationId":"delete_task","parameters":[{"name":"id","in":"path","description":"Task ID","required":true,"schema":{"type":"string","format":"uuid"}}],"responses":{"204":{"description":"Task deleted"},"404":{"description":"Task not found"}}},"patch":{"tags":["tasks"],"operationId":"update_task","parameters":[{"name":"id","in":"path","description":"Task ID","required":true,"schema":{"type":"string","format":"uuid"}}],"requestBody":{"content":{"application/json":{"schema":{"$ref":"#/components/schemas/UpdateTaskRequest"}}},"required":true},"responses":{"200":{"description":"Task updated","content":{"application/json":{"schema":{"$ref":"#/components/schemas/Task"}}}},"400":{"description":"Validation error"},"404":{"description":"Task not found"}}}},"/health":{"get":{"tags":["health"],"operationId":"health_check","responses":{"200":{"description":"Service is healthy","content":{"text/plain":{"schema":{"type":"string"}}}}}}}},"components":{"schemas":{"AddMemberRequest":{"type":"object","required":["user_id","role"],"properties":{"role":{"$ref":"#/components/schemas/MemberRole"},"user_id":{"type":"string","format":"uuid"}}},"CreateProjectRequest":{"type":"object","required":["name"],"properties":{"description":{"type":["string","null"]},"name":{"type":"string"}}},"CreateTaskRequest":{"type":"object","required":["project_id","title"],"properties":{"assigned_to":{"type":["string","null"],"format":"uuid"},"description":{"type":["string","null"]},"parent_id":{"type":["string","null"],"format":"uuid"},"priority":{"oneOf":[{"type":"null"},{"$ref":"#/components/schemas/TaskPriority"}]},"project_id":{"type":"string","format":"uuid"},"status":{"oneOf":[{"type":"null"},{"$ref":"#/components/schemas/TaskStatus"}]},"title":{"type":"string"}}},"MemberRole":{"type":"string","enum":["owner","admin","member"]},"Project":{"type":"object","required":["id","name","created_at","updated_at"],"properties":{"created_at":{"type":"string","format":"date-time"},"description":{"type":["string","null"]},"id":{"type":"string","format":"uuid"},"name":{"type":"string"},"updated_at":{"type":"string","format":"date-time"}}},"ProjectMember":{"type":"object","required":["project_id","user_id","role","created_at"],"properties":{"created_at":{"type":"string","format":"date-time"},"project_id":{"type":"string","format":"uuid"},"role":{"$ref":"#/components/schemas/MemberRole"},"user_id":{"type":"string","format":"uuid"}}},"Task":{"type":"object","required":["id","project_id","title","status","priority","position","created_at","updated_at"],"properties":{"assigned_to":{"type":["string","null"],"format":"uuid"},"created_at":{"type":"string","format":"date-time"},"description":{"type":["string","null"]},"id":{"type":"string","format":"uuid"},"parent_id":{"type":["string","null"],"format":"uuid"},"position":{"type":"integer","format":"int32"},"priority":{"$ref":"#/components/schemas/TaskPriority"},"project_id":{"type":"string","format":"uuid"},"status":{"$ref":"#/components/schemas/TaskStatus"},"title":{"type":"string"},"updated_at":{"type":"string","format":"date-time"}}},"TaskPriority":{"type":"string","enum":["low","medium","high","urgent"]},"TaskStatus":{"type":"string","enum":["backlog","todo","in_progress","in_review","done"]},"UpdateMemberRequest":{"type":"object","required":["role"],"properties":{"role":{"$ref":"#/components/schemas/MemberRole"}}},"UpdateProjectRequest":{"type":"object","properties":{"description":{"type":["string","null"]},"name":{"type":["string","null"]}}},"UpdateTaskRequest":{"type":"object","properties":{"assigned_to":{"type":["string","null"],"format":"uuid"},"description":{"type":["string","null"]},"parent_id":{"type":["string","null"],"format":"uuid"},"position":{"type":["integer","null"],"format":"int32"},"priority":{"oneOf":[{"type":"null"},{"$ref":"#/components/schemas/TaskPriority"}]},"status":{"oneOf":[{"type":"null"},{"$ref":"#/components/schemas/TaskStatus"}]},"title":{"type":["string","null"]}}},"User":{"type":"object","required":["id","name","email","created_at","updated_at"],"properties":{"created_at":{"type":"string","format":"date-time"},"email":{"type":"string"},"id":{"type":"string","format":"uuid"},"name":{"type":"string"},"updated_at":{"type":"string","format":"date-time"}}},"WsMessage":{"oneOf":[{"type":"object","required":["task","type"],"properties":{"task":{"$ref":"#/components/schemas/Task"},"type":{"type":"string","enum":["TaskCreated"]}}},{"type":"object","required":["task","type"],"properties":{"task":{"$ref":"#/components/schemas/Task"},"type":{"type":"string","enum":["TaskUpdated"]}}},{"type":"object","required":["task_id","type"],"properties":{"task_id":{"type":"string","format":"uuid"},"type":{"type":"string","enum":["TaskDeleted"]}}}]}}},"tags":[{"name":"health","description":"Health check"},{"name":"tasks","description":"Task management"},{"name":"projects","description":"Project management"},{"name":"project-members","description":"Project member management"}]}